tfe22540/CN2.py
tfe22540/Corpus_callosum_division.py
tfe22540/Corpus_callosum_reg.py
tfe22540/DMD_before_reg.py
tfe22540/DTI_kmeans_clustering.py
tfe22540/DTI_tissue_classification.py
tfe22540/FA_DMD.py
tfe22540/Stat_test.py
tfe22540/__init__.py
tfe22540/analyse_ttest.py
tfe22540/atlas_modif_name.py
tfe22540/atlas_registration.py
tfe22540/clustering.py
tfe22540/clustering_v2.py
tfe22540/comportement.py
tfe22540/dMRI_metric_reg.py
tfe22540/diamond_fractions.py
tfe22540/f0_f1_to_ftot.py
tfe22540/job_submission.py
tfe22540/moyenne_ROI_v2.py
tfe22540/moyenne_par_ROI.py
tfe22540/opening_closing.py
tfe22540/perso_path.py
tfe22540/plot_functions.py
tfe22540/preprocessing.py
tfe22540/registration.py
tfe22540/ttest.py
tfe22540/useful_fct.py
tfe22540/volumes_zones.py
alcoholic_tfe22540-0.1.5.dist-info/METADATA
alcoholic_tfe22540-0.1.5.dist-info/WHEEL
alcoholic_tfe22540-0.1.5.dist-info/top_level.txt
alcoholic_tfe22540-0.1.5.dist-info/RECORD
